LICENSE
nanoqa/__init__.py
nanoqa/components/__init__.py
nanoqa/components/document_store/__init__.py
nanoqa/components/document_store/lexical.py
nanoqa/components/file_processing/__init__.py
nanoqa/components/file_processing/convertors/__init__.py
nanoqa/components/file_processing/convertors/docx.py
nanoqa/components/file_processing/convertors/pdf.py
nanoqa/components/file_processing/convertors/txt.py
nanoqa/components/file_processing/text_processor/__init__.py
nanoqa/components/file_processing/text_processor/preprocessor.py
nanoqa/components/file_processing/utils.py
nanoqa/components/file_processing/x2pdf.py
nanoqa/components/question_answering/__init__.py
nanoqa/components/question_answering/handlers/__init__.py
nanoqa/components/question_answering/handlers/inference.py
nanoqa/components/question_answering/handlers/train.py
nanoqa/components/question_answering/pipeline/__init__.py
nanoqa/components/question_answering/pipeline/es.py
nanoqa/components/question_answering/ranker/__init__.py
nanoqa/components/question_answering/ranker/cross_encoder.py
nanoqa/components/question_answering/reader/__init__.py
nanoqa/components/question_answering/reader/adapter.py
nanoqa/components/question_answering/reader/base.py
nanoqa/components/question_answering/retriever/__init__.py
nanoqa/components/question_answering/retriever/base.py
nanoqa/components/question_answering/tokenization.py
nanoqa/components/rich_utils.py
nanoqa/configs.py
nanoqa/schemas/__init__.py
nanoqa/schemas/pipeline/__init__.py
nanoqa/schemas/pipeline/pipeline_schemas.py
nanoqa/schemas/reader/__init__.py
nanoqa/schemas/reader/reader_args.py
nanoqa/schemas/reader/reader_schemas.py
nanoqa/schemas/retriever/__init__.py
nanoqa/schemas/retriever/retriever_schemas.py
nanoqa/static/Roboto-Regular.ttf
nanoqa-0.0.40.dist-info/LICENSE
nanoqa-0.0.40.dist-info/WHEEL
nanoqa-0.0.40.dist-info/entry_points.txt
nanoqa-0.0.40.dist-info/METADATA
nanoqa-0.0.40.dist-info/RECORD
