Metadata-Version: 2.1
Name: nanoqa
Version: 0.0.40
Summary: 
Home-page: https://github.com/gabinguo/nanoQA
License: Apache
Keywords: Question Answering,Huggingface Transformers
Author: Kunpeng GUO
Author-email: gabin.guo@gmail.com
Requires-Python: >=3.8,<4.0
Classifier: License :: Other/Proprietary License
Classifier: Programming Language :: Python :: 3
Classifier: Programming Language :: Python :: 3.8
Classifier: Programming Language :: Python :: 3.9
Classifier: Programming Language :: Python :: 3.10
Classifier: Programming Language :: Python :: 3.11
Requires-Dist: PyMuPDF (==1.21.1)
Requires-Dist: adapter-transformers (==3.1.0)
Requires-Dist: datasets (==2.9.0)
Requires-Dist: docx2python (==2.6.0)
Requires-Dist: elasticsearch (==7.17.4)
Requires-Dist: fpdf2 (==2.6.1)
Requires-Dist: mmh3 (==3.0.0)
Requires-Dist: more_itertools (==9.0.0)
Requires-Dist: nltk (==3.8.1)
Requires-Dist: rich (==13.3.1)
Requires-Dist: wheel (==0.38.4)
Project-URL: Repository, https://github.com/gabinguo/nanoQA
